requestsplus/__init__.py
requestsplus-0.0.6.dist-info/DESCRIPTION.rst
requestsplus-0.0.6.dist-info/METADATA
requestsplus-0.0.6.dist-info/RECORD
requestsplus-0.0.6.dist-info/WHEEL
requestsplus-0.0.6.dist-info/metadata.json
requestsplus-0.0.6.dist-info/top_level.txt
requestsplus-0.0.6.dist-info/zip-safe
